whurl/__init__.py
whurl/client.py
whurl/exceptions.py
whurl/schemas/mixins.py
whurl/schemas/requests/__init__.py
whurl/schemas/requests/base.py
whurl/schemas/requests/collection_list.py
whurl/schemas/requests/get_data.py
whurl/schemas/requests/measurement_list.py
whurl/schemas/requests/site_info.py
whurl/schemas/requests/site_list.py
whurl/schemas/requests/status.py
whurl/schemas/requests/time_range.py
whurl/schemas/responses/__init__.py
whurl/schemas/responses/collection_list.py
whurl/schemas/responses/get_data.py
whurl/schemas/responses/measurement_list.py
whurl/schemas/responses/site_info.py
whurl/schemas/responses/site_list.py
whurl/schemas/responses/status.py
whurl/schemas/responses/time_range.py
whurl/utils.py
whurl-0.1.0.dist-info/METADATA
whurl-0.1.0.dist-info/WHEEL
whurl-0.1.0.dist-info/licenses/LICENSE
whurl-0.1.0.dist-info/RECORD
