Metadata-Version: 2.4
Name: whurl
Version: 0.1.0
Summary: Which Hydro URL? - Python API wrapper for Hilltop Server
License-Expression: GPL-3.0-or-later
License-File: LICENSE
Author: nicmostert
Author-email: nicolas.mostert@horizons.govt.nz
Requires-Python: >=3.11,<4.0
Classifier: Development Status :: 4 - Beta
Classifier: Intended Audience :: Developers
Classifier: License :: OSI Approved :: GNU General Public License v3 (GPLv3)
Classifier: Programming Language :: Python :: 3.11
Classifier: Programming Language :: Python :: 3.12
Classifier: Programming Language :: Python :: 3.13
Classifier: Programming Language :: Python :: 3.14
Classifier: Topic :: Software Development :: Libraries
Classifier: Topic :: Software Development :: Libraries :: Python Modules
Requires-Dist: anyio (>=4.10.0,<5.0.0)
Requires-Dist: certifi (>=2025.8.3,<2026.0.0)
Requires-Dist: fastapi (>=0.116.1,<0.117.0)
Requires-Dist: h2 (>=4.3.0,<5.0.0)
Requires-Dist: httpx (>=0.28.1,<0.29.0)
Requires-Dist: isodate (>=0.7.2,<0.8.0)
Requires-Dist: lxml (>=6.0.1,<7.0.0)
Requires-Dist: numpy (>=1.26.4,<2.0.0)
Requires-Dist: pandas (>=2.3.2,<3.0.0)
Requires-Dist: poetry (>=2.2.1,<3.0.0)
Requires-Dist: pydantic (>=2.11.9,<3.0.0)
Requires-Dist: pytest (>=8.4.2,<9.0.0)
Requires-Dist: pytest-asyncio (>=1.2.0,<2.0.0)
Requires-Dist: pytest-benchmark (>=5.1.0,<6.0.0)
Requires-Dist: pytest-cov (>=7.0.0,<8.0.0)
Requires-Dist: pytest-httpx (>=0.35.0,<0.36.0)
Requires-Dist: pytest-mock (>=3.15.0,<4.0.0)
Requires-Dist: python-dotenv (>=1.1.1,<2.0.0)
Requires-Dist: pyyaml (>=6.0.2,<7.0.0)
Requires-Dist: uvicorn (>=0.35.0,<0.36.0)
Requires-Dist: xmltodict (>=1.0.0,<2.0.0)
